[
   {
      "rank": 1,
      "name": "Ruihan Li",
      "score": 616
   },
   {
      "rank": 2,
      "name": "jiangjianfeng",
      "score": 355
   },
   {
      "rank": 3,
      "name": "Chengjun Chen",
      "score": 335
   },
   {
      "rank": 4,
      "name": "Qingsong Chen",
      "score": 252
   },
   {
      "rank": 5,
      "name": "Junyang Zhang",
      "score": 235
   },
   {
      "rank": 6,
      "name": "Wang Siyuan",
      "score": 218
   },
   {
      "rank": 7,
      "name": "Xinyi Yu",
      "score": 204
   },
   {
      "rank": 8,
      "name": "Tate, Hongliang Tian",
      "score": 197
   },
   {
      "rank": 9,
      "name": "Tao Su",
      "score": 141
   },
   {
      "rank": 10,
      "name": "li041",
      "score": 137
   },
   {
      "rank": 11,
      "name": "wyt8",
      "score": 100
   },
   {
      "rank": 12,
      "name": "zjp",
      "score": 61
   },
   {
      "rank": 13,
      "name": "vvsv",
      "score": 44
   },
   {
      "rank": 14,
      "name": "Zhenchen Wang",
      "score": 39
   },
   {
      "rank": 15,
      "name": "Cautreoxit",
      "score": 38
   },
   {
      "rank": 16,
      "name": "Marsman1996",
      "score": 37
   },
   {
      "rank": 17,
      "name": "Aaron Chen",
      "score": 30
   },
   {
      "rank": 18,
      "name": "Hsy-Intel",
      "score": 28
   },
   {
      "rank": 19,
      "name": "zzj-5341",
      "score": 27
   },
   {
      "rank": 20,
      "name": "Chaoqun Zheng",
      "score": 24
   },
   {
      "rank": 21,
      "name": "TankTechnology",
      "score": 20
   },
   {
      "rank": 22,
      "name": "yyda",
      "score": 12
   },
   {
      "rank": 23,
      "name": "Wei Zhang",
      "score": 11
   },
   {
      "rank": 24,
      "name": "Junrui Luo",
      "score": 10
   },
   {
      "rank": 25,
      "name": "Yuke Peng",
      "score": 10
   },
   {
      "rank": 26,
      "name": "Ray Lee",
      "score": 9
   },
   {
      "rank": 27,
      "name": "Chao Liu",
      "score": 9
   },
   {
      "rank": 28,
      "name": "rikosellic",
      "score": 8
   },
   {
      "rank": 29,
      "name": "Zhihang Shao",
      "score": 7
   },
   {
      "rank": 30,
      "name": "YanLien",
      "score": 6
   },
   {
      "rank": 31,
      "name": "asterinas",
      "score": 6
   },
   {
      "rank": 32,
      "name": "Chaoqun Zheng",
      "score": 6
   },
   {
      "rank": 33,
      "name": "dependabot[bot]",
      "score": 4
   },
   {
      "rank": 34,
      "name": "wheatfox",
      "score": 3
   },
   {
      "rank": 35,
      "name": "lxh",
      "score": 2
   },
   {
      "rank": 36,
      "name": "Arthur Paulino",
      "score": 2
   },
   {
      "rank": 37,
      "name": "wrj97",
      "score": 2
   },
   {
      "rank": 38,
      "name": "root",
      "score": 2
   },
   {
      "rank": 39,
      "name": "zzjrabbit",
      "score": 2
   },
   {
      "rank": 40,
      "name": "Jakob Hellermann",
      "score": 2
   },
   {
      "rank": 41,
      "name": "John Hughes",
      "score": 2
   },
   {
      "rank": 42,
      "name": "Calvin",
      "score": 2
   }
]
